scheduler/__init__.py
scheduler/admin/__init__.py
scheduler/admin/job.py
scheduler/admin/redis_models.py
scheduler/apps.py
scheduler/decorators.py
scheduler/management/__init__.py
scheduler/management/commands/__init__.py
scheduler/management/commands/delete_failed_executions.py
scheduler/management/commands/export.py
scheduler/management/commands/import.py
scheduler/management/commands/rqstats.py
scheduler/management/commands/rqworker.py
scheduler/management/commands/run_job.py
scheduler/migrations/0001_initial_squashed_0005_added_result_ttl.py
scheduler/migrations/0002_alter_cronjob_id_alter_repeatablejob_id_and_more.py
scheduler/migrations/0003_auto_20220329_2107.py
scheduler/migrations/0004_cronjob_at_front_repeatablejob_at_front_and_more.py
scheduler/migrations/0005_alter_cronjob_at_front_alter_repeatablejob_at_front_and_more.py
scheduler/migrations/0006_auto_20230118_1640.py
scheduler/migrations/0007_add_result_ttl.py
scheduler/migrations/0008_rename_str_val_jobarg_val_and_more.py
scheduler/migrations/0009_alter_jobarg_arg_type_alter_jobarg_val_and_more.py
scheduler/migrations/0010_queue.py
scheduler/migrations/0011_worker_alter_queue_options_alter_cronjob_at_front_and_more.py
scheduler/migrations/0012_alter_cronjob_name_alter_repeatablejob_name_and_more.py
scheduler/migrations/0013_alter_cronjob_queue_alter_repeatablejob_queue_and_more.py
scheduler/migrations/__init__.py
scheduler/models/__init__.py
scheduler/models/args.py
scheduler/models/queue.py
scheduler/models/scheduled_job.py
scheduler/models/worker.py
scheduler/py.typed
scheduler/queues.py
scheduler/rq_classes.py
scheduler/settings.py
scheduler/templates/admin/scheduler/change_form.html
scheduler/templates/admin/scheduler/change_list.html
scheduler/templates/admin/scheduler/confirm_action.html
scheduler/templates/admin/scheduler/job_detail.html
scheduler/templates/admin/scheduler/jobs-list.partial.html
scheduler/templates/admin/scheduler/jobs.html
django_rq_scheduler-2023.9.0.dist-info/LICENSE
django_rq_scheduler-2023.9.0.dist-info/METADATA
django_rq_scheduler-2023.9.0.dist-info/WHEEL
django_rq_scheduler-2023.9.0.dist-info/RECORD
